neatlog/__init__.py
neatlog/log_decorator.py
neatlog/log_fmt.py
neatlog-0.1.8.dist-info/LICENSE
neatlog-0.1.8.dist-info/WHEEL
neatlog-0.1.8.dist-info/METADATA
neatlog-0.1.8.dist-info/RECORD
