Metadata-Version: 2.1
Name: neatlog
Version: 0.1.8
Summary: A neat logging configurator
Home-page: https://gitlab.com/szs/neatlog/
License: MIT
Keywords: logging
Author: Steffen Brinkmann
Author-email: s-b@mailbox.org
Requires-Python: >=3.6.1,<4.0.0
Classifier: Development Status :: 4 - Beta
Classifier: Environment :: Console
Classifier: License :: OSI Approved :: MIT License
Classifier: Operating System :: POSIX
Classifier: Programming Language :: Python :: 3
Classifier: Programming Language :: Python :: 3.6
Classifier: Programming Language :: Python :: 3.7
Classifier: Programming Language :: Python :: 3.8
Classifier: Programming Language :: Python :: 3.9
Classifier: Topic :: System :: Logging
Classifier: Topic :: System :: Shells
Classifier: Topic :: Terminals
Project-URL: Documentation, https://neatlog.readthedocs.io/en/latest/
Project-URL: Repository, https://gitlab.com/szs/neatlog/
